robotnikai/__init__.py
robotnikai/api_client.py
robotnikai/api_response.py
robotnikai/configuration.py
robotnikai/exceptions.py
robotnikai/py.typed
robotnikai/rest.py
robotnikai/wrapper.py
robotnikai/api/__init__.py
robotnikai/api/applications_actions_webhooks_api.py
robotnikai/api/applications_api.py
robotnikai/api/applications_tables_api.py
robotnikai/api/applications_tables_csv_export_api.py
robotnikai/api/applications_tables_csv_import_api.py
robotnikai/api/applications_tables_graph_ql_api.py
robotnikai/api/applications_tables_tags_api.py
robotnikai/api/integrations_api.py
robotnikai/api/integrations_api_calls_api.py
robotnikai/api/integrations_email_service_api.py
robotnikai/api/plugin_interfaces_plugins_api.py
robotnikai/api/plugins_api.py
robotnikai/models/__init__.py
robotnikai/models/api_key_distribution_enum.py
robotnikai/models/apps_graphql_playground_app_parameter.py
robotnikai/models/apps_graphql_query400_response.py
robotnikai/models/apps_graphql_query401_response.py
robotnikai/models/apps_graphql_query404_response.py
robotnikai/models/get_connections200_response_inner.py
robotnikai/models/get_list200_response_inner.py
robotnikai/models/graph_ql_request.py
robotnikai/models/graph_ql_response.py
robotnikai/models/graph_ql_response_errors_inner.py
robotnikai/models/graph_ql_response_errors_inner_locations_inner.py
robotnikai/models/hmac_algorithm_enum.py
robotnikai/models/hmac_key_format_enum.py
robotnikai/models/integration.py
robotnikai/models/integration_category.py
robotnikai/models/integration_type.py
robotnikai/models/invoke_parallel_call200_response.py
robotnikai/models/invoke_parallel_call_connection_id_parameter.py
robotnikai/models/invoke_parallel_call_for_connection200_response.py
robotnikai/models/invoke_parallel_call_for_connection_connection_id_parameter.py
robotnikai/models/invoke_parallel_call_for_connection_request.py
robotnikai/models/invoke_parallel_call_for_connection_request_data_list_inner.py
robotnikai-0.2.6.dist-info/METADATA
robotnikai-0.2.6.dist-info/WHEEL
robotnikai-0.2.6.dist-info/top_level.txt
robotnikai-0.2.6.dist-info/RECORD
